[{"name":"Steak vita","id":"b38f9a90-3110-4c47-8a26-7ade9eeb6135","uom":"g","quantity":250.0,"category":"Steak","price":50.0},{"name":"Steak vita","id":"e644051b-9be5-4e47-940a-21dfd96583b9","quantity":250.0,"price":50.0,"uom":"g","category":"Steak"},{"name":"Steak vita","id":"082d5143-1417-4e97-a386-21a652d42727","quantity":250.0,"price":50.0,"category":"Steak","uom":"g"},{"name":"Steak vita","id":"cdf7b8ac-6aec-47a5-b03a-e4076fa4640f","quantity":250.0,"price":50.0,"uom":"g","category":"Steak"},{"name":"Steak vita","id":"d52dae20-c730-4c6c-9cb7-c75eb126c583","category":"Steak","price":50.0,"uom":"g","quantity":250.0},{"name":"Steak vita","id":"61f29dd6-6647-469b-aeeb-f7d3964123c7","category":"Steak","quantity":250.0,"price":50.0,"uom":"g"},{"name":"Steak vita","id":"dacfd489-1d2f-4182-86d4-6f8e3288841f","quantity":250.0,"price":50.0,"uom":"g","category":"Steak"}]